mdoutline/VERSION
mdoutline/__init__.py
mdoutline/main.py
mdoutline/version.py
mdoutline-0.0.1.dist-info/LICENSE
mdoutline-0.0.1.dist-info/METADATA
mdoutline-0.0.1.dist-info/WHEEL
mdoutline-0.0.1.dist-info/entry_points.txt
mdoutline-0.0.1.dist-info/top_level.txt
mdoutline-0.0.1.dist-info/RECORD
