Metadata-Version: 2.1
Name: mdoutline
Version: 0.0.1
Summary: 📝
Home-page: https://github.com/rishiraj/mdoutline
Author: Rishiraj Acharya
Author-email: heyrishiraj@gmail.com
Classifier: Programming Language :: Python :: 3
Classifier: License :: OSI Approved :: GNU General Public License v3 (GPLv3)
Classifier: Operating System :: OS Independent
Requires-Python: >=3.9
License-File: LICENSE
